bfb_delivery/__init__.py
bfb_delivery/api/__init__.py
bfb_delivery/api/internal.py
bfb_delivery/api/public.py
bfb_delivery/cli/__init__.py
bfb_delivery/cli/build_routes_from_chunked.py
bfb_delivery/cli/combine_route_tables.py
bfb_delivery/cli/create_manifests.py
bfb_delivery/cli/create_manifests_from_circuit.py
bfb_delivery/cli/format_combined_routes.py
bfb_delivery/cli/split_chunked_route.py
bfb_delivery/lib/__init__.py
bfb_delivery/lib/constants.py
bfb_delivery/lib/errors.py
bfb_delivery/lib/utils.py
bfb_delivery/lib/dispatch/__init__.py
bfb_delivery/lib/dispatch/api_callers.py
bfb_delivery/lib/dispatch/read_circuit.py
bfb_delivery/lib/dispatch/utils.py
bfb_delivery/lib/dispatch/write_to_circuit.py
bfb_delivery/lib/formatting/__init__.py
bfb_delivery/lib/formatting/data_cleaning.py
bfb_delivery/lib/formatting/sheet_shaping.py
bfb_delivery/lib/formatting/utils.py
bfb_delivery/lib/schema/__init__.py
bfb_delivery/lib/schema/schema.py
bfb_delivery/lib/schema/utils.py
bfb_delivery/lib/schema/checks/__init__.py
bfb_delivery/lib/schema/checks/dataframe_checks.py
bfb_delivery/lib/schema/checks/field_checks.py
bfb_delivery-2.0.3.dist-info/licenses/LICENSE
bfb_delivery-2.0.3.dist-info/METADATA
bfb_delivery-2.0.3.dist-info/WHEEL
bfb_delivery-2.0.3.dist-info/entry_points.txt
bfb_delivery-2.0.3.dist-info/top_level.txt
bfb_delivery-2.0.3.dist-info/RECORD
