Metadata-Version: 2.4
Name: bfb_delivery
Version: 2.0.3
Summary: Tools to help plan deliveries for Bellingham Food Bank.
Author: Kaleb Coberly
Maintainer-email: kaleb.coberly@gmail.com
Requires-Python: >=3.12
License-File: LICENSE
Requires-Dist: click<9.0.0,>=8.1.8
Requires-Dist: comb_utils<1.0.0,>=0.2.0
Requires-Dist: email-validator<3.0.0,>=2.2.0
Requires-Dist: openpyxl<4.0.0,>=3.1.5
Requires-Dist: pandera[extensions]<0.23.0,>=0.22.1
Requires-Dist: phonenumbers<9.0.0,>=8.13.52
Requires-Dist: python-dotenv<2.0.0,>=1.0.1
Requires-Dist: typeguard<5.0.0,>=4.4.1
Requires-Dist: requests<3.0.0,>=2.32.3
Requires-Dist: requests-mock<2.0.0,>=1.12.1
Requires-Dist: numpy<2.4.0,>=2.0.0
Requires-Dist: pandas<2.4.0,>=2.3.0
Provides-Extra: dev
Requires-Dist: bfb_delivery[build]; extra == "dev"
Requires-Dist: bfb_delivery[doc]; extra == "dev"
Requires-Dist: bfb_delivery[qc]; extra == "dev"
Requires-Dist: bfb_delivery[test]; extra == "dev"
Provides-Extra: build
Requires-Dist: build; extra == "build"
Requires-Dist: twine; extra == "build"
Requires-Dist: wheel; extra == "build"
Provides-Extra: doc
Requires-Dist: furo>=2023.5.20; extra == "doc"
Requires-Dist: sphinx<8.2.0,>=7.0.1; extra == "doc"
Requires-Dist: sphinx-autodoc-typehints>=1.23.3; extra == "doc"
Requires-Dist: sphinx-click; extra == "doc"
Requires-Dist: sphinxcontrib-mermaid<2.0.0,>=1.0.0; extra == "doc"
Provides-Extra: qc
Requires-Dist: bandit>=1.7; extra == "qc"
Requires-Dist: black>=23.3; extra == "qc"
Requires-Dist: flake8>=6.0.0; extra == "qc"
Requires-Dist: flake8-annotations>=3.0.1; extra == "qc"
Requires-Dist: flake8-bandit>=4.1.1; extra == "qc"
Requires-Dist: flake8-black>=0.4.0; extra == "qc"
Requires-Dist: flake8-bugbear>=23.7.10; extra == "qc"
Requires-Dist: flake8-docstrings>=1.7.0; extra == "qc"
Requires-Dist: flake8-isort>=6.0.0; extra == "qc"
Requires-Dist: isort>=5.12.0; extra == "qc"
Requires-Dist: jake>=3.0.1; extra == "qc"
Requires-Dist: pytype>=2023.6.0; python_version < "3.13" and extra == "qc"
Requires-Dist: bfb_delivery[test]; extra == "qc"
Requires-Dist: safety>=2.3.1; extra == "qc"
Provides-Extra: test
Requires-Dist: coverage[toml]>=7.2.7; extra == "test"
Requires-Dist: pydantic-core>=2.41.5; extra == "test"
Requires-Dist: pytest>=7.4.0; extra == "test"
Requires-Dist: pytest-cov>=4.1; extra == "test"
Dynamic: license-file
